{
    "menu": [
        {
            "directory": "Welcome",
            "title": "Welcome",
            "color": "orange",
            "submenus": [
                {
                    "file": "Introduction",
                    "title": "Getting Started"
                },
                {
                    "file": "Platform",
                    "title": "The Cloud Platform"
                },
                {
                    "file": "OnBoarding",
                    "title": "OnBoarding Explained"
                },
                {
                    "file": "DevicesPage",
                    "title": "Understanding the Devices Page"
                },
                {
                    "file": "Sensors",
                    "title": "Making Sense of Sensors"
                },
                {
                    "file": "MM",
                    "title": "Mastering the Master (Module)"
                },
                {
                    "file": "OAuthReference",
                    "title": "OAuth Reference"
                },
                {
                    "file": "Roadmap",
                    "title": "What's ahead? - Roadmap"
                }
            ]
        },
        {
            "directory": "Authorization",
            "title": "Authorization",
            "color": "purple",
            "submenus": [
                {
                    "file": "Reference",
                    "title": "Introduction"
                }
                                
            ]
        },
        {
            "directory": "relayrAPI",
            "title": "relayr API",
            "color": "blue",
            "submenus": [
                {
                    "file": "Introduction",
                    "title": "Introduction"
                },
                {
                    "file": "relayrAPI", 
                    "title": "The relayr API",
                    "external": "/dashboard/api",
                    "newTab": true
                },
                {
                    "file": "ImportAPI",
                    "title": "Importing the API into Postman"
                }
            ]
        },
        {
            "directory": "Android",
            "title": "Android",
            "color": "green",
            "icon": "fa-android",
            "submenus": [
                {
                    "file": "Reference",
                    "title": "Introduction"
                },
                {
                    "file": "BuildingApp",
                    "title": "Building your first relayr Android App"
                },
                {
                    "file": "Sample Project",
                    "title": "Sample App - Thermometer",
                    "external": "https://github.com/relayr/android-demo-apps/tree/master/thermometer",
                    "newTab": true
                },
                {
                    "file": "Sample Project",
                    "title": "Sample App - CantTouchThis",
                    "external": "https://github.com/relayr/android-cant-touch-this",
                    "newTab": true
                },
                {
                    "file": "Sample Project",
                    "title": "Sample App - TellMeWhen",
                    "external": "https://github.com/relayr/android-tell-me-when",
                    "newTab": true
                },
                {
                    "file": "SDK Documentation",
                    "title": "SDK Reference",
                    "external": "/rendered-doc/javadoc/index.html",
                    "newTab": true
                }
            ]
        },
        {
            "directory": "Apple",
            "title": "iOS/OSX",
            "color": "yellow",
            "icon" : "",
            "submenus": [
                {
                    "file": "Introduction",
                    "title": "Introduction"
                },
                {
                    "file": "FirstApp",
                    "title": "Building your first relayr iOS/OSX App"
                },
                {
                    "file": "Classes",
                    "title": "Basic Classes"
                },
                {
                    "file": "Sample Project",
                    "title": "Sample App - Thermometer",
                    "external": "https://github.com/relayr/apple-sample-apps/tree/thermometer",
                    "newTab": true
                },
                {
                    "file": "Sample Project",
                    "title": "Sample App - TellMeWhen",
                    "external": "https://github.com/relayr/apple-tell-me-when",
                    "newTab": true
                },
                {
                    "file": "Sample Project",
                    "title": "Executable Code Samples",
                    "external": "https://github.com/relayr/apple-sample-apps/tree/master/code-samples",
                    "newTab": true
                }
            ]
        },
        {
            "directory": "Python",
            "title": "Python",
            "color": "yellow",
            "icon" : "",
            "submenus": [
                {
                    "file": "Introduction",
                    "title": "Getting Started"
                },
                {
                    "file": "Python Reference",
                    "title": "Full Reference",
                    "external": "http://relayr.readthedocs.org/",
                    "newTab": true
                }
            ]
        },
        {
            "directory": "WebDev",
            "title": "Web Development",
            "color": "yellow",
            "icon" : "fa-apple",
            "submenus": [
                {
                    "file": "Introduction",
                    "title": "Introduction"
                },
                {
                    "file": "WebDevelopers",
                    "title": "Web Browser Development"
                },
                {
                    "file": "The JavaScript SDK",
                    "title": "The JavaScript SDK",
                    "external": "https://github.com/relayr/browser-sdk",
                    "newTab": true
                },
                {
                    "file": "OAuthToken",
                    "title": "Getting your OAuth App Token"
                },
                {
                    "file": "Sample Project",
                    "title": "Sample App - CantTouchThis",
                    "external": "https://github.com/relayr/cantTouchThis",
                    "newTab": true
                }
            ]
        },
        {
            "directory": "Nodejs",
            "title": "Node.js",
            "color": "yellow",
            "icon" : "fa-apple",
            "submenus": [
                {
                    "file": "Reference",
                    "title": "Introduction"
                },
                {
                    "file": "Library",
                    "title": "The Node.js Library",
                    "external": "https://github.com/relayr/node-relayr",
                    "newTab": true
                }
            ]
        },
        {
            "directory": "CSharp",
            "title": "C#",
            "color": "yellow",
            "icon" : "fa-apple",
            "submenus": [
                {
                    "file": "Reference",
                    "title": "Introduction"
                },
                {
                    "file": "MyFirstApp",
                    "title": "Building your first relayr C# App"
                },
                {
                    "file": "The C# SDK",
                    "title": "The C# SDK",
                    "external": "https://github.com/relayr/csharp-sdk",
                    "newTab": true
                }
            ]
        },
        {
            "directory": "HowTos",
            "title": "Firmware Extras",
            "color": "purple",
            "submenus": [
                {
                    "file": "Introduction",
                    "title": "Introduction"
                },
                {
                    "file": "Flashing",
                    "title": "Replacing the Firmware on a Sensor Module"
                },
                {
                    "file": "iBeacons",
                    "title": "Using Sensor Modules as iBeacons"
                },
                {
                    "file": "Arduino",
                    "title": "Connecing the relayr Bridge to Arduino"
                },
                {
                    "file": "WunderBarSchem",
                    "title": "The WunderBar Layout and Schematics"
                }    
            ]
        }
    ]
}
